tj_kits_mount/__init__.py
tj_kits_mount/tj_kits.py
tj_kits_mount-0.0.1.dist-info/METADATA
tj_kits_mount-0.0.1.dist-info/WHEEL
tj_kits_mount-0.0.1.dist-info/top_level.txt
tj_kits_mount-0.0.1.dist-info/RECORD
