Metadata-Version: 2.1
Name: tj-kits-mount
Version: 0.0.1
Summary: Some Kits
Home-page: https://github.com/TJNo-1/tj_kits_mount.git
Author: tjno-1
Author-email: tjno-1@qq.com
License: MIT
Keywords: python,build-in-module kits
